pachcalib/__init__.py
pachcalib/api/__init__.py
pachcalib/api/ipachca.py
pachcalib/api/models/__init__.py
pachcalib/api/models/api_models.py
pachcalib/api/models/base_models.py
pachcalib/api/models/constants.py
pachcalib/api/pachca_impl.py
pachcalib/py.typed
pachcalib-0.1.3.dist-info/WHEEL
pachcalib-0.1.3.dist-info/METADATA
pachcalib-0.1.3.dist-info/RECORD
