Metadata-Version: 2.3
Name: pachcalib
Version: 0.1.3
Summary: This library was done for easy interaction with Pachca Messenger
Author: Владислав Кузнецов
Author-email: Владислав Кузнецов <v.kuznetsov@ideco.ru>
Requires-Dist: aiohttp>=3.12.15
Requires-Dist: isort>=6.0.1
Requires-Dist: pydantic>=2.11.9
Requires-Dist: uv-build>=0.8.22
Requires-Dist: uvloop>=0.21.0
Requires-Python: >=3.13
